{
  "parent": "minecraft:recipes/root",
  "rewards": {
    "recipes": [
      "ilikewood:cypress_post_from_cypress_log_sawmilling"
    ]
  },
  "criteria": {
    "has_log": {
      "trigger": "minecraft:inventory_changed",
      "conditions": {
        "items": [
          {
            "items": [
              "byg:cypress_log"
            ]
          }
        ]
      }
    },
    "has_the_recipe": {
      "trigger": "minecraft:recipe_unlocked",
      "conditions": {
        "recipe": "ilikewood:cypress_post_from_cypress_log_sawmilling"
      }
    }
  },
  "requirements": [
    [
      "has_log",
      "has_the_recipe"
    ]
  ]
}